whooshes/__init__.py
whooshes/_version.py
whooshes/conftest.py
whooshes/transformer.py
whooshes/elasticsearch/__init__.py
whooshes/elasticsearch/transformer.py
whooshes/elasticsearch/tests/__init__.py
whooshes/elasticsearch/tests/test_es_query_transformer.py
whooshes/ext/__init__.py
whooshes/ext/analyzers.py
whooshes/ext/fields.py
WhooshES-0.1.dist-info/LICENSE
WhooshES-0.1.dist-info/METADATA
WhooshES-0.1.dist-info/WHEEL
WhooshES-0.1.dist-info/top_level.txt
WhooshES-0.1.dist-info/RECORD
