Metadata-Version: 2.1
Name: WhooshES
Version: 0.1
Summary: Whoosh & Elasticsearch compatibility toolkit
Home-page: https://github.com/aiudirog/WhooshES
Author: Roger Aiudi
Author-email: aiudirog@gmail.com
License: MIT
Keywords: utils,helpers,asyncio
Platform: UNKNOWN
Classifier: Development Status :: 3 - Alpha
Classifier: Intended Audience :: Developers
Classifier: License :: OSI Approved :: MIT License
Classifier: Programming Language :: Python :: 3.6
Classifier: Programming Language :: Python :: 3.7
Classifier: Programming Language :: Python :: 3.8
Classifier: Programming Language :: Python :: 3.9
Classifier: Programming Language :: Python :: 3.10
Classifier: Programming Language :: Python :: Implementation :: CPython
Classifier: Programming Language :: Python :: Implementation :: PyPy
Classifier: Topic :: Software Development :: Libraries :: Python Modules
Requires-Python: >=3.6
License-File: LICENSE
